ratemyprofessor/__init__.py
ratemyprofessor/professor.py
ratemyprofessor/school.py
ratemyprofessor/json/header.json
ratemyprofessor/json/professorquery.json
ratemyprofessor/json/ratingsquery.json
RateMyProfessorAPI-1.3.4.dist-info/LICENSE
RateMyProfessorAPI-1.3.4.dist-info/METADATA
RateMyProfessorAPI-1.3.4.dist-info/WHEEL
RateMyProfessorAPI-1.3.4.dist-info/top_level.txt
RateMyProfessorAPI-1.3.4.dist-info/RECORD
