Metadata-Version: 2.1
Name: RateMyProfessorAPI
Version: 1.3.4
Summary: Python web scraper to get professor ratings from ratemyprofessor.com website.
Home-page: https://github.com/Nobelz/RateMyProfessorAPI
Author: Nobel Zhou
Author-email: nxz157@case.edu
Project-URL: Issue Tracker, https://github.com/Nobelz/RateMyProfessorAPI/issues
Classifier: Development Status :: 3 - Alpha
Classifier: Intended Audience :: Developers
Classifier: Topic :: Software Development
Classifier: License :: OSI Approved :: Apache Software License
Classifier: Programming Language :: Python :: 3
Classifier: Programming Language :: Python :: 3.5
Classifier: Programming Language :: Python :: 3.6
Classifier: Programming Language :: Python :: 3.7
Classifier: Programming Language :: Python :: 3.8
Classifier: Programming Language :: Python :: 3.9
Requires-Python: >=3.5
License-File: LICENSE
Requires-Dist: requests
Requires-Dist: beautifulsoup4
Requires-Dist: lxml
